{
  "lessonId": 10,
  "lessonTitle": "Theory of Cognitive Resonance 2",
  "generatedAt": "2026-02-22T09:23:54.351Z",
  "questions": [
    {
      "id": 1,
      "question": "According to the lesson, what is the main problem with the idea that 'I' choose my thoughts?",
      "correct_answer": "The 'I' that should choose the thought is itself a product of the thought process, creating a closed circle.",
      "difficulty": "easy",
      "points": 5
    },
    {
      "id": 2,
      "question": "In the radio receiver model of consciousness, what happens when cognitive resonance occurs?",
      "correct_answer": "The signal of that thought is sharply amplified while all others are filtered out, like when a radio receiver's frequency matches a station's frequency.",
      "difficulty": "easy",
      "points": 5
    },
    {
      "id": 3,
      "question": "What is knowledge according to this lesson?",
      "correct_answer": "Knowledge is an abstraction connected with a sign.",
      "difficulty": "easy",
      "points": 5
    },
    {
      "id": 4,
      "question": "According to the author, what does it mean to remember something?",
      "correct_answer": "To remember means to tune your heterodyne to the frequency of the preserved pattern and obtain resonance.",
      "difficulty": "easy",
      "points": 5
    },
    {
      "id": 5,
      "question": "What does the author say is the proper way to teach thinking?",
      "correct_answer": "To teach thinking means training the process of tuning by developing abilities to distinguish, compare, abstract, and creating conditions for resonance, rather than filling memory with ready-made patterns.",
      "difficulty": "easy",
      "points": 5
    }
  ]
}